fx_requi/__init__.py
fx_requi-0.1.0.dist-info/METADATA
fx_requi-0.1.0.dist-info/WHEEL
fx_requi-0.1.0.dist-info/entry_points.txt
fx_requi-0.1.0.dist-info/top_level.txt
fx_requi-0.1.0.dist-info/RECORD
