Metadata-Version: 2.1
Name: fx_requi
Version: 0.1.0
Summary: Утилита для генерации requirements.txt на основе импортов в проекте
Author: Maxim
Author-email: firi8228@gmail.com
Classifier: Programming Language :: Python :: 3
Classifier: License :: OSI Approved :: MIT License
Classifier: Operating System :: OS Independent
Requires-Python: >=3.6
